picometer/__init__.py
picometer/__main__.py
picometer/atom.py
picometer/instructions.py
picometer/logging.py
picometer/models.py
picometer/process.py
picometer/settings.py
picometer/settings.yaml
picometer/shapes.py
picometer/utility.py
picometer-0.5.0.dist-info/LICENSE
picometer-0.5.0.dist-info/METADATA
picometer-0.5.0.dist-info/WHEEL
picometer-0.5.0.dist-info/RECORD
