Metadata-Version: 2.3
Name: picometer
Version: 0.5.0
Summary: Precisely define and calculate measurements across multiple crystal structures
License: MIT
Author: Daniel Tchoń
Requires-Python: >=3.10
Classifier: License :: OSI Approved :: MIT License
Classifier: Programming Language :: Python :: 3
Classifier: Programming Language :: Python :: 3.10
Classifier: Programming Language :: Python :: 3.11
Classifier: Programming Language :: Python :: 3.12
Classifier: Programming Language :: Python :: 3.13
Requires-Dist: hikari-toolkit (>=0.2.3)
Requires-Dist: numpy (>=2)
Requires-Dist: pandas (>=2)
Requires-Dist: pyyaml (>=5)
Requires-Dist: uncertainties (>=3)
